facedis/__init__.py
facedis/face_compare.py
faces_distance-0.0.1.dist-info/METADATA
faces_distance-0.0.1.dist-info/WHEEL
faces_distance-0.0.1.dist-info/top_level.txt
faces_distance-0.0.1.dist-info/RECORD
